[
  {
    "id": 1,
    "subject": "Welcome to the Company - Important",
    "sender": "hr@company.internal",
    "receiver": "employee19@giriaryan694-a11y.github.io",
    "time": "09:15 AM",
    "mdFile": "md/welcome.md",
    "hasAttachment": false,
    "unread": true
  },
  {
    "id": 2,
    "subject": "Urgent: Password Reset Required",
    "sender": "it-support@company.internal",
    "receiver": "employee19@giriaryan694-a11y.github.io",
    "time": "Yesterday",
    "mdFile": "md/phishing-alert.md",
    "hasAttachment": true,
    "attachmentName": "password_reset_form.pdf",
    "unread": true
  }
]
